gibson2/__init__.py
gibson2/global_config.yaml
gibson2/core/.gitignore
gibson2/core/__init__.py
gibson2/core/__init__.pyc
gibson2/core/simulator.py
gibson2/core/__pycache__/__init__.cpython-35.pyc
gibson2/core/__pycache__/__init__.cpython-36.pyc
gibson2/core/__pycache__/mujoco_bridge.cpython-36.pyc
gibson2/core/__pycache__/simulator.cpython-35.pyc
gibson2/core/__pycache__/simulator.cpython-36.pyc
gibson2/core/physics/.gitignore
gibson2/core/physics/__init__.py
gibson2/core/physics/interactive_objects.py
gibson2/core/physics/robot_bases.py
gibson2/core/physics/robot_locomotors.py
gibson2/core/physics/scene.py
gibson2/core/physics/__pycache__/__init__.cpython-35.pyc
gibson2/core/physics/__pycache__/__init__.cpython-36.pyc
gibson2/core/physics/__pycache__/interactive_objects.cpython-35.pyc
gibson2/core/physics/__pycache__/interactive_objects.cpython-36.pyc
gibson2/core/physics/__pycache__/robot_bases.cpython-35.pyc
gibson2/core/physics/__pycache__/robot_bases.cpython-36.pyc
gibson2/core/physics/__pycache__/robot_locomotors.cpython-35.pyc
gibson2/core/physics/__pycache__/robot_locomotors.cpython-36.pyc
gibson2/core/physics/__pycache__/scene.cpython-35.pyc
gibson2/core/physics/__pycache__/scene.cpython-36.pyc
gibson2/core/physics/drivers/__init__.py
gibson2/core/physics/drivers/minitaur.py
gibson2/core/physics/drivers/motor.py
gibson2/core/render/.gitignore
gibson2/core/render/CMakeLists.txt
gibson2/core/render/__init__.py
gibson2/core/render/__init__.pyc
gibson2/core/render/profiler.py
gibson2/core/render/profiler.pyc
gibson2/core/render/utils.py
gibson2/core/render/viewer.py
gibson2/core/render/vision_utils.py
gibson2/core/render/.idea/.name
gibson2/core/render/.idea/misc.xml
gibson2/core/render/.idea/modules.xml
gibson2/core/render/.idea/render.iml
gibson2/core/render/.idea/vcs.xml
gibson2/core/render/.idea/workspace.xml
gibson2/core/render/__pycache__/__init__.cpython-35.pyc
gibson2-0.0.5.dist-info/METADATA
gibson2-0.0.5.dist-info/RECORD
gibson2-0.0.5.dist-info/WHEEL
gibson2-0.0.5.dist-info/top_level.txt
