Metadata-Version: 2.1
Name: gibson2
Version: 0.0.5
Summary: UNKNOWN
Home-page: https://github.com/StanfordVL/iGibson
Author: Stanford University
License: UNKNOWN
Platform: UNKNOWN
